[
  {
    "id": "_ucdGz_`|N-2025-01-06T17:25:39Z",
    "etr": "ETR-NULL",
    "etrConfidence": null,
    "cluster": false,
    "comments": "Power problem is being assessed. A restoration estimate is in progress.",
    "cause": "Pending crew assessment",
    "numberOut": 1,
    "custAffected": 4,
    "crewStatus": null,
    "startTime": "2025-01-06T17:25:39Z",
    "latitude": 42.78624,
    "longitude": -83.39982,
    "source": "https://kubra.io/cluster-data/201/227de1f9-4adc-4fc9-98cb-dc2b847c0549/01a74ed4-0a3a-4162-9ca5-216c317a80d9/public/cluster-1/03022320121102.json"
  },
  {
    "id": "ufddG~|_|N-2025-01-06T16:19:02Z",
    "etr": "2025-01-06T19:50:00Z",
    "etrConfidence": null,
    "cluster": false,
    "comments": null,
    "cause": "Equipment problem",
    "numberOut": 1,
    "custAffected": 19,
    "crewStatus": null,
    "startTime": "2025-01-06T16:19:02Z",
    "latitude": 42.78907,
    "longitude": -83.39936,
    "source": "https://kubra.io/cluster-data/201/227de1f9-4adc-4fc9-98cb-dc2b847c0549/01a74ed4-0a3a-4162-9ca5-216c317a80d9/public/cluster-1/03022320121102.json"
  },
  {
    "id": "upxbGfw|zN-2025-01-06T12:19:08Z",
    "etr": "2025-01-06T19:45:00Z",
    "etrConfidence": null,
    "cluster": false,
    "comments": null,
    "cause": "Equipment problem",
    "numberOut": 1,
    "custAffected": 4,
    "crewStatus": null,
    "startTime": "2025-01-06T12:19:08Z",
    "latitude": 42.56539,
    "longitude": -83.21924,
    "source": "https://kubra.io/cluster-data/223/227de1f9-4adc-4fc9-98cb-dc2b847c0549/01a74ed4-0a3a-4162-9ca5-216c317a80d9/public/cluster-1/03022320132322.json"
  },
  {
    "id": "m_ybGzv|zN-2025-01-06T12:39:33Z",
    "etr": "2025-01-07T12:35:00Z",
    "etrConfidence": null,
    "cluster": false,
    "comments": null,
    "cause": "Equipment problem",
    "numberOut": 1,
    "custAffected": 4,
    "crewStatus": null,
    "startTime": "2025-01-06T12:39:33Z",
    "latitude": 42.56775,
    "longitude": -83.21918,
    "source": "https://kubra.io/cluster-data/223/227de1f9-4adc-4fc9-98cb-dc2b847c0549/01a74ed4-0a3a-4162-9ca5-216c317a80d9/public/cluster-1/03022320132322.json"
  },
  {
    "id": "asqaGflm|N-2025-01-06T16:17:28.697Z",
    "etr": "2025-01-06T18:30:00Z",
    "etrConfidence": null,
    "cluster": false,
    "comments": null,
    "cause": "Reqd to repair/upgrade equip",
    "numberOut": 1,
    "custAffected": 4,
    "crewStatus": null,
    "startTime": "2025-01-06T16:17:28.697Z",
    "latitude": 42.36609,
    "longitude": -83.46836,
    "source": "https://kubra.io/cluster-data/303/227de1f9-4adc-4fc9-98cb-dc2b847c0549/01a74ed4-0a3a-4162-9ca5-216c317a80d9/public/cluster-1/03022320303.json"
  },
  {
    "id": "gssaGxc~{N-2025-01-06T14:46:10Z",
    "etr": "2025-01-06T20:30:00Z",
    "etrConfidence": null,
    "cluster": false,
    "comments": null,
    "cause": "Equipment problem",
    "numberOut": 1,
    "custAffected": 4,
    "crewStatus": null,
    "startTime": "2025-01-06T14:46:10Z",
    "latitude": 42.37636,
    "longitude": -83.39021,
    "source": "https://kubra.io/cluster-data/302/227de1f9-4adc-4fc9-98cb-dc2b847c0549/01a74ed4-0a3a-4162-9ca5-216c317a80d9/public/cluster-1/030223203.json"
  },
  {
    "id": "}klaGnmk|N-2025-01-06T15:41:31.724Z",
    "etr": "2025-01-06T18:00:00Z",
    "etrConfidence": null,
    "cluster": false,
    "comments": null,
    "cause": "Reqd to repair/upgrade equip",
    "numberOut": 1,
    "custAffected": 4,
    "crewStatus": null,
    "startTime": "2025-01-06T15:41:31.724Z",
    "latitude": 42.33935,
    "longitude": -83.45832,
    "source": "https://kubra.io/cluster-data/303/227de1f9-4adc-4fc9-98cb-dc2b847c0549/01a74ed4-0a3a-4162-9ca5-216c317a80d9/public/cluster-1/03022320303.json"
  },
  {
    "id": "qqsaGluozN-2025-01-06T16:26:00.540Z",
    "etr": "2025-01-06T19:30:00Z",
    "etrConfidence": null,
    "cluster": false,
    "comments": null,
    "cause": "Reqd to repair/upgrade equip",
    "numberOut": 1,
    "custAffected": 4,
    "crewStatus": null,
    "startTime": "2025-01-06T16:26:00.540Z",
    "latitude": 42.37609,
    "longitude": -83.15239,
    "source": "https://kubra.io/cluster-data/130/227de1f9-4adc-4fc9-98cb-dc2b847c0549/01a74ed4-0a3a-4162-9ca5-216c317a80d9/public/cluster-1/0302232031.json"
  },
  {
    "id": "qg{`Gxsk{N-2025-01-06T16:45:38Z",
    "etr": "2025-01-07T16:55:00Z",
    "etrConfidence": null,
    "cluster": false,
    "comments": null,
    "cause": "Equipment problem",
    "numberOut": 1,
    "custAffected": 4,
    "crewStatus": null,
    "startTime": "2025-01-06T16:45:38Z",
    "latitude": 42.25161,
    "longitude": -83.29549,
    "source": "https://kubra.io/cluster-data/033/227de1f9-4adc-4fc9-98cb-dc2b847c0549/01a74ed4-0a3a-4162-9ca5-216c317a80d9/public/cluster-1/03022320330.json"
  },
  {
    "id": "acaaGt{i{N-2025-01-06T17:31:28Z",
    "etr": "ETR-NULL",
    "etrConfidence": null,
    "cluster": false,
    "comments": "Power problem is being assessed. A restoration estimate is in progress.",
    "cause": "Pending crew assessment",
    "numberOut": 1,
    "custAffected": 4,
    "crewStatus": null,
    "startTime": "2025-01-06T17:31:28Z",
    "latitude": 42.28161,
    "longitude": -83.28651,
    "source": "https://kubra.io/cluster-data/033/227de1f9-4adc-4fc9-98cb-dc2b847c0549/01a74ed4-0a3a-4162-9ca5-216c317a80d9/public/cluster-1/03022320330.json"
  },
  {
    "id": "emo`Gvl_{N-2025-01-06T01:46:02Z",
    "etr": "2025-01-07T01:45:00Z",
    "etrConfidence": null,
    "cluster": false,
    "comments": null,
    "cause": "Equipment problem",
    "numberOut": 1,
    "custAffected": 4,
    "crewStatus": null,
    "startTime": "2025-01-06T01:46:02Z",
    "latitude": 42.19107,
    "longitude": -83.23292,
    "source": "https://kubra.io/cluster-data/330/227de1f9-4adc-4fc9-98cb-dc2b847c0549/01a74ed4-0a3a-4162-9ca5-216c317a80d9/public/cluster-1/0302232033.json"
  },
  {
    "id": "q~s`G|jwzN-2025-01-06T13:57:02Z",
    "etr": "2025-01-07T14:15:00Z",
    "etrConfidence": null,
    "cluster": false,
    "comments": null,
    "cause": "Pending crew assessment",
    "numberOut": 1,
    "custAffected": 4,
    "crewStatus": null,
    "startTime": "2025-01-06T13:57:02Z",
    "latitude": 42.21433,
    "longitude": -83.19167,
    "source": "https://kubra.io/cluster-data/330/227de1f9-4adc-4fc9-98cb-dc2b847c0549/01a74ed4-0a3a-4162-9ca5-216c317a80d9/public/cluster-1/0302232033.json"
  },
  {
    "id": "amaaGtdmzN-2025-01-06T15:15:17Z",
    "etr": "2025-01-07T15:30:00Z",
    "etrConfidence": null,
    "cluster": false,
    "comments": null,
    "cause": "Pending crew assessment",
    "numberOut": 1,
    "custAffected": 4,
    "crewStatus": null,
    "startTime": "2025-01-06T15:15:17Z",
    "latitude": 42.28321,
    "longitude": -83.13947,
    "source": "https://kubra.io/cluster-data/302/227de1f9-4adc-4fc9-98cb-dc2b847c0549/01a74ed4-0a3a-4162-9ca5-216c317a80d9/public/cluster-1/030223203.json"
  },
  {
    "id": "kzsaG`t`zN-2025-01-06T16:21:24Z",
    "etr": "2025-01-07T16:20:00Z",
    "etrConfidence": null,
    "cluster": false,
    "comments": null,
    "cause": "Equipment problem",
    "numberOut": 1,
    "custAffected": 4,
    "crewStatus": null,
    "startTime": "2025-01-06T16:21:24Z",
    "latitude": 42.3775,
    "longitude": -83.07537,
    "source": "https://kubra.io/cluster-data/130/227de1f9-4adc-4fc9-98cb-dc2b847c0549/01a74ed4-0a3a-4162-9ca5-216c317a80d9/public/cluster-1/0302232031.json"
  },
  {
    "id": "apwaG~gjzN-2025-01-06T15:46:41Z",
    "etr": "2025-01-07T15:45:00Z",
    "etrConfidence": null,
    "cluster": false,
    "comments": null,
    "cause": "Equipment problem",
    "numberOut": 1,
    "custAffected": 4,
    "crewStatus": null,
    "startTime": "2025-01-06T15:46:41Z",
    "latitude": 42.39633,
    "longitude": -83.12464,
    "source": "https://kubra.io/cluster-data/130/227de1f9-4adc-4fc9-98cb-dc2b847c0549/01a74ed4-0a3a-4162-9ca5-216c317a80d9/public/cluster-1/0302232031.json"
  },
  {
    "id": "klkaGbjbzN-2025-01-06T17:28:20Z",
    "etr": "ETR-NULL",
    "etrConfidence": null,
    "cluster": false,
    "comments": "Power problem is being assessed. A restoration estimate is in progress.",
    "cause": "Pending crew assessment",
    "numberOut": 1,
    "custAffected": 4,
    "crewStatus": null,
    "startTime": "2025-01-06T17:28:20Z",
    "latitude": 42.3343,
    "longitude": -83.08402,
    "source": "https://kubra.io/cluster-data/130/227de1f9-4adc-4fc9-98cb-dc2b847c0549/01a74ed4-0a3a-4162-9ca5-216c317a80d9/public/cluster-1/0302232031.json"
  },
  {
    "id": "ablaGvgxyN-2025-01-06T14:51:54Z",
    "etr": "2025-01-06T18:20:00Z",
    "etrConfidence": null,
    "cluster": false,
    "comments": null,
    "cause": "Problem with customer equipment",
    "numberOut": 1,
    "custAffected": 4,
    "crewStatus": null,
    "startTime": "2025-01-06T14:51:54Z",
    "latitude": 42.33777,
    "longitude": -83.03244,
    "source": "https://kubra.io/cluster-data/130/227de1f9-4adc-4fc9-98cb-dc2b847c0549/01a74ed4-0a3a-4162-9ca5-216c317a80d9/public/cluster-1/0302232031.json"
  },
  {
    "id": "inmbG|}czN-2025-01-06T15:36:55Z",
    "etr": "2025-01-07T15:35:00Z",
    "etrConfidence": null,
    "cluster": false,
    "comments": null,
    "cause": "Pending crew assessment",
    "numberOut": 1,
    "custAffected": 4,
    "crewStatus": null,
    "startTime": "2025-01-06T15:36:55Z",
    "latitude": 42.50869,
    "longitude": -83.09231,
    "source": "https://kubra.io/cluster-data/302/227de1f9-4adc-4fc9-98cb-dc2b847c0549/01a74ed4-0a3a-4162-9ca5-216c317a80d9/public/cluster-1/030223203.json"
  },
  {
    "id": "se}bGjk~yN-2025-01-05T14:43:51Z",
    "etr": "2025-01-07T15:20:00Z",
    "etrConfidence": null,
    "cluster": false,
    "comments": null,
    "cause": "Pending crew assessment",
    "numberOut": 1,
    "custAffected": 4,
    "crewStatus": null,
    "startTime": "2025-01-05T14:43:51Z",
    "latitude": 42.58922,
    "longitude": -83.06374,
    "source": "https://kubra.io/cluster-data/310/227de1f9-4adc-4fc9-98cb-dc2b847c0549/01a74ed4-0a3a-4162-9ca5-216c317a80d9/public/cluster-1/0302232013.json"
  },
  {
    "id": "eufcGvzxyN-2025-01-06T02:31:11Z",
    "etr": "2025-01-07T11:50:00Z",
    "etrConfidence": null,
    "cluster": false,
    "comments": null,
    "cause": "Pending crew assessment",
    "numberOut": 1,
    "custAffected": 4,
    "crewStatus": null,
    "startTime": "2025-01-06T02:31:11Z",
    "latitude": 42.63779,
    "longitude": -83.03548,
    "source": "https://kubra.io/cluster-data/310/227de1f9-4adc-4fc9-98cb-dc2b847c0549/01a74ed4-0a3a-4162-9ca5-216c317a80d9/public/cluster-1/0302232013.json"
  },
  {
    "id": "a}bcGrjgzN-2025-01-06T16:56:27Z",
    "etr": "2025-01-07T16:55:00Z",
    "etrConfidence": null,
    "cluster": false,
    "comments": null,
    "cause": "Equipment problem",
    "numberOut": 1,
    "custAffected": 4,
    "crewStatus": null,
    "startTime": "2025-01-06T16:56:27Z",
    "latitude": 42.61857,
    "longitude": -83.1097,
    "source": "https://kubra.io/cluster-data/310/227de1f9-4adc-4fc9-98cb-dc2b847c0549/01a74ed4-0a3a-4162-9ca5-216c317a80d9/public/cluster-1/0302232013.json"
  },
  {
    "id": "ytdcGripzN-2025-01-06T16:58:58Z",
    "etr": "2025-01-07T16:55:00Z",
    "etrConfidence": null,
    "cluster": false,
    "comments": null,
    "cause": "Pending crew assessment",
    "numberOut": 1,
    "custAffected": 4,
    "crewStatus": null,
    "startTime": "2025-01-06T16:58:58Z",
    "latitude": 42.62749,
    "longitude": -83.15562,
    "source": "https://kubra.io/cluster-data/310/227de1f9-4adc-4fc9-98cb-dc2b847c0549/01a74ed4-0a3a-4162-9ca5-216c317a80d9/public/cluster-1/0302232013.json"
  },
  {
    "id": "wqjcG|tv{N-2025-01-06T16:10:49Z",
    "etr": "2025-01-07T16:10:00Z",
    "etrConfidence": null,
    "cluster": false,
    "comments": null,
    "cause": "Equipment problem",
    "numberOut": 1,
    "custAffected": 4,
    "crewStatus": null,
    "startTime": "2025-01-06T16:10:49Z",
    "latitude": 42.65772,
    "longitude": -83.35199,
    "source": "https://kubra.io/cluster-data/023/227de1f9-4adc-4fc9-98cb-dc2b847c0549/01a74ed4-0a3a-4162-9ca5-216c317a80d9/public/cluster-1/03022320.json"
  },
  {
    "id": "gjhbGfd}|N-2025-01-03T23:37:52Z",
    "etr": "2025-01-06T19:35:00Z",
    "etrConfidence": null,
    "cluster": false,
    "comments": null,
    "cause": "Equipment problem",
    "numberOut": 1,
    "custAffected": 4,
    "crewStatus": null,
    "startTime": "2025-01-03T23:37:52Z",
    "latitude": 42.48244,
    "longitude": -83.549,
    "source": "https://kubra.io/cluster-data/232/227de1f9-4adc-4fc9-98cb-dc2b847c0549/01a74ed4-0a3a-4162-9ca5-216c317a80d9/public/cluster-1/0302232.json"
  },
  {
    "id": "cspaGvte_O-2025-01-06T17:07:40Z",
    "etr": "ETR-NULL",
    "etrConfidence": null,
    "cluster": false,
    "comments": "Power problem is being assessed. A restoration estimate is in progress.",
    "cause": "Pending crew assessment",
    "numberOut": 1,
    "custAffected": 19,
    "crewStatus": null,
    "startTime": "2025-01-06T17:07:40Z",
    "latitude": 42.36098,
    "longitude": -83.92028,
    "source": "https://kubra.io/cluster-data/023/227de1f9-4adc-4fc9-98cb-dc2b847c0549/01a74ed4-0a3a-4162-9ca5-216c317a80d9/public/cluster-1/03022320.json"
  },
  {
    "id": "gvrbGllt~N-2025-01-06T16:32:22Z",
    "etr": "2025-01-07T16:30:00Z",
    "etrConfidence": null,
    "cluster": false,
    "comments": null,
    "cause": "Equipment problem",
    "numberOut": 1,
    "custAffected": 4,
    "crewStatus": null,
    "startTime": "2025-01-06T16:32:22Z",
    "latitude": 42.53556,
    "longitude": -83.83191,
    "source": "https://kubra.io/cluster-data/202/227de1f9-4adc-4fc9-98cb-dc2b847c0549/01a74ed4-0a3a-4162-9ca5-216c317a80d9/public/cluster-1/030223202.json"
  },
  {
    "id": "}izaGf_q~N-2025-01-06T13:47:18Z",
    "etr": "2025-01-07T13:45:00Z",
    "etrConfidence": null,
    "cluster": false,
    "comments": null,
    "cause": "Equipment problem",
    "numberOut": 1,
    "custAffected": 4,
    "crewStatus": null,
    "startTime": "2025-01-06T13:47:18Z",
    "latitude": 42.41071,
    "longitude": -83.81444,
    "source": "https://kubra.io/cluster-data/202/227de1f9-4adc-4fc9-98cb-dc2b847c0549/01a74ed4-0a3a-4162-9ca5-216c317a80d9/public/cluster-1/030223202.json"
  },
  {
    "id": "axaaG`kh~N-2025-01-06T15:06:16Z",
    "etr": "2025-01-06T18:35:00Z",
    "etrConfidence": null,
    "cluster": false,
    "comments": null,
    "cause": "Reqd to repair/upgrade equip",
    "numberOut": 1,
    "custAffected": 4,
    "crewStatus": null,
    "startTime": "2025-01-06T15:06:16Z",
    "latitude": 42.28497,
    "longitude": -83.77025,
    "source": "https://kubra.io/cluster-data/132/227de1f9-4adc-4fc9-98cb-dc2b847c0549/01a74ed4-0a3a-4162-9ca5-216c317a80d9/public/cluster-1/03022320231.json"
  },
  {
    "id": "_b~`Gtle~N-2025-01-06T15:52:00.800Z",
    "etr": "2025-01-06T19:20:00Z",
    "etrConfidence": null,
    "cluster": false,
    "comments": null,
    "cause": "Reqd to repair/upgrade equip",
    "numberOut": 1,
    "custAffected": 9,
    "crewStatus": null,
    "startTime": "2025-01-06T15:52:00.800Z",
    "latitude": 42.26608,
    "longitude": -83.75515,
    "source": "https://kubra.io/cluster-data/132/227de1f9-4adc-4fc9-98cb-dc2b847c0549/01a74ed4-0a3a-4162-9ca5-216c317a80d9/public/cluster-1/03022320231.json"
  },
  {
    "id": "ey{`Gfpz}N-2025-01-06T15:23:27.109Z",
    "etr": "ETR-EXP",
    "etrConfidence": null,
    "cluster": false,
    "comments": null,
    "cause": "Reqd to repair/upgrade equip",
    "numberOut": 1,
    "custAffected": 4,
    "crewStatus": null,
    "startTime": "2025-01-06T15:23:27.109Z",
    "latitude": 42.25443,
    "longitude": -83.6994,
    "source": "https://kubra.io/cluster-data/320/227de1f9-4adc-4fc9-98cb-dc2b847c0549/01a74ed4-0a3a-4162-9ca5-216c317a80d9/public/cluster-1/0302232023.json"
  },
  {
    "id": "klbiGhttzN-2025-01-06T16:45:01Z",
    "etr": "2025-01-07T16:45:00Z",
    "etrConfidence": null,
    "cluster": false,
    "comments": null,
    "cause": "Pending crew assessment",
    "numberOut": 1,
    "custAffected": 4,
    "crewStatus": null,
    "startTime": "2025-01-06T16:45:01Z",
    "latitude": 43.59894,
    "longitude": -83.17781,
    "source": "https://kubra.io/cluster-data/032/227de1f9-4adc-4fc9-98cb-dc2b847c0549/01a74ed4-0a3a-4162-9ca5-216c317a80d9/public/cluster-1/0302230.json"
  },
  {
    "id": "gc`hGjsoxN-2025-01-06T16:45:23Z",
    "etr": "2025-01-06T20:30:00Z",
    "etrConfidence": null,
    "cluster": false,
    "comments": null,
    "cause": "Reqd to repair/upgrade equip",
    "numberOut": 1,
    "custAffected": 8,
    "crewStatus": null,
    "startTime": "2025-01-06T16:45:23Z",
    "latitude": 43.4234,
    "longitude": -82.82438,
    "source": "https://kubra.io/cluster-data/032/227de1f9-4adc-4fc9-98cb-dc2b847c0549/01a74ed4-0a3a-4162-9ca5-216c317a80d9/public/cluster-1/0302230.json"
  }
]